__init__.py
berita_terbaru_cnn/__init__.py
newsfeed_cnn_indonesia-0.0.2.dist-info/licenses/LICENSE
newsfeed_cnn_indonesia-0.0.2.dist-info/METADATA
newsfeed_cnn_indonesia-0.0.2.dist-info/WHEEL
newsfeed_cnn_indonesia-0.0.2.dist-info/top_level.txt
newsfeed_cnn_indonesia-0.0.2.dist-info/RECORD
