Metadata-Version: 2.4
Name: NewsFeed-CNN-Indonesia
Version: 0.0.2
Summary: 6 Popular news from CNN Indonesia
Author-email: Remote-Idn <rsatriawan@gmail.com>
License-Expression: GPL-3.0-only
Project-URL: Homepage, https://github.com/Remote-Idn/News-Feed
Project-URL: Issues, https://remote-idn.com
Classifier: Programming Language :: Python :: 3
Classifier: Operating System :: OS Independent
Classifier: Development Status :: 5 - Production/Stable
Requires-Python: >=3.9
License-File: LICENSE
Dynamic: license-file
